{
  "addCharacter": [
    {
      "name": "Baloo",
      "age:": 32,
      "gender": "male",
      "level": 5,
      "healthPoints": 10,
      "strength": 5,
      "dexterity": 9,
      "intelligence": 4,
      "wisdom": 15,
      "constitution": 8,
      "charisma": 15,
      "backstory": "living life",
      "professionName": "enjoyer of life",
      "speciesName": "none"
    }
  ],
  "resumeStory": [
    { "id": "1", "name": "Stayin Alive", "summery": "Bla bla bla bla bla" }
  ],
  "user": [{ "email": "hej@test.com", "password:": "test123" }]
}
